{
  "id": 26,
  "section": "Binnenland",
  "topic": "Binnenland",
  "level": "A2",
  "title": "Adoptie uit buitenland werd 'gepauzeerd', maar nu staan er toch weer 35 gezinnen in de wachtrij",
  "topicNumber": 1,
  "article": {
    "title": "Adoptie uit buitenland werd 'gepauzeerd', maar nu staan er toch weer 35 gezinnen in de wachtrij",
    "summary": "Veertig gezinnen in Vlaanderen zijn bezig met een traject voor buitenlandse adoptie, 35 andere werd beloofd dat ze er nog mogen instappen. En dat terwijl er al sinds eind 2023 een 'adoptiepauze' is afgekondigd. 'De boodschap is niet helder en dat is lastig', meent parlementslid Freya Perdaens (N-VA)."
  },
  "vocabulary": {
    "words": [
      {
        "word": "buitenland",
        "definition": "andere landen, niet het eigen land",
        "sentence": "Sommige kinderen komen uit het ___.",
        "answer": "buitenland"
      },
      {
        "word": "pauze",
        "definition": "een korte stop of onderbreking",
        "sentence": "De adoptie werd even ___ gezet.",
        "answer": "pauze"
      },
      {
        "word": "parlementslid",
        "definition": "een persoon die in het parlement werkt, de volksvertegenwoordiger",
        "sentence": "Een ___ geeft commentaar op de situatie.",
        "answer": "parlementslid"
      },
      {
        "word": "boodschap",
        "definition": "een bericht of mededeling",
        "sentence": "De ___ van de overheid was niet duidelijk.",
        "answer": "boodschap"
      },
      {
        "word": "wachtrij",
        "definition": "een lijst of rij van mensen die wachten",
        "sentence": "Er staan veel mensen in de ___ voor adoptie.",
        "answer": "wachtrij"
      }
    ],
    "fillInBlanks": [
      {
        "sentence": "De ___ van de overheid was niet duidelijk.",
        "answer": "boodschap"
      },
      {
        "sentence": "Sommige kinderen komen uit het ___.",
        "answer": "buitenland"
      },
      {
        "sentence": "Er staan veel mensen in de ___ voor adoptie.",
        "answer": "wachtrij"
      }
    ]
  },
  "multipleChoice": [
    {
      "question": "Waar ging de adoptiepauze over?",
      "options": [
        "Het tijdelijk stoppen van adoptie uit het buitenland",
        "Het versnellen van adoptieprocedures",
        "Het helpen van gezinnen in de wachtrij",
        "Het annuleren van alle adoptieverzoeken"
      ],
      "correctAnswer": 1
    },
    {
      "question": "Wat is de rol van een parlementslid in deze context?",
      "options": [
        "Het maken van nieuwe wetten",
        "Het geven van commentaar op situaties",
        "Het leiden van adoptieprocedures",
        "Het ondersteunen van adoptiegezinnen financieel"
      ],
      "correctAnswer": 2
    },
    {
      "question": "Wat betekent 'wachtrij' in deze tekst?",
      "options": [
        "Een soort van attractie in een pretpark",
        "Een lange rij mensen die wachten",
        "Een speciale rij voor adoptiegezinnen",
        "Een tijdelijke stop van processen"
      ],
      "correctAnswer": 2
    }
  ],
  "trueFalse": [
    {
      "statement": "Adoptie uit het buitenland is helemaal gestopt in Vlaanderen.",
      "isTrue": false
    },
    {
      "statement": "Een parlementslid geeft commentaar op de adoptiepauze.",
      "isTrue": true
    },
    {
      "statement": "Er zijn nu meer dan 100 gezinnen in de wachtrij voor adoptie.",
      "isTrue": false
    }
  ]
}