{
  "id": 21,
  "section": "Binnenland",
  "topic": "Binnenland",
  "level": "B1",
  "title": "Defensie werkt aan betere droneverdediging",
  "topicNumber": 1,
  "article": {
    "title": "Defensie werkt aan betere droneverdediging",
    "summary": "Defensie wil haar bescherming tegen drones verbeteren. Ze gaan nieuwe technologie kopen om drones te detecteren en te bestrijden. Dit gebeurt na incidenten waarbij drones ongezien bases naderden."
  },
  "vocabulary": {
    "words": [
      {
        "word": "Defensie",
        "definition": "de krijgsmacht, het leger",
        "sentence": "___ is de organisatie die het land verdedigt.",
        "answer": "Defensie"
      },
      {
        "word": "drones",
        "definition": "onbemande vliegtuigjes, vaak op afstand bestuurd",
        "sentence": "Een ___ is een klein onbemand vliegtuigje.",
        "answer": "drone"
      },
      {
        "word": "detecteren",
        "definition": "opmerken, ontdekken",
        "sentence": "De politie kan een verdachte ___ met camera's.",
        "answer": "detecteren"
      },
      {
        "word": "verbeteren",
        "definition": "beter maken, verbeteren",
        "sentence": "De coach wil de teamspirit ___ met oefeningen.",
        "answer": "verbeteren"
      }
    ],
    "fillInBlanks": [
      {
        "sentence": "Een ___ is een klein onbemand vliegtuigje.",
        "answer": "drone"
      },
      {
        "sentence": "De coach wil de teamspirit ___ met oefeningen.",
        "answer": "verbeteren"
      },
      {
        "sentence": "De politie kan een verdachte ___ met camera's.",
        "answer": "detecteren"
      }
    ]
  },
  "multipleChoice": [
    {
      "question": "Wat is het doel van Defensie volgens de tekst?",
      "options": [
        "Drone races organiseren",
        "Nieuwe drones kopen voor eigen gebruik",
        "Drone detectie en bewapening verbeteren",
        "Geen actie ondernemen"
      ],
      "correctAnswer": 3
    },
    {
      "question": "Waarom wil Defensie deze actie ondernemen?",
      "options": [
        "Omdat er een tekort is aan drones",
        "Omdat er recent incidenten waren met drones",
        "Omdat de regering het heeft gevraagd",
        "Omdat het budget te hoog is"
      ],
      "correctAnswer": 2
    },
    {
      "question": "Hoe reageert Defensie op de drone-incidenten?",
      "options": [
        "Door drones te negeren",
        "Door defensiebudgetten te verhogen zonder actie",
        "Door technologie te kopen voor betere detectie",
        "Door de luchtmacht op te doeken"
      ],
      "correctAnswer": 3
    }
  ],
  "trueFalse": [
    {
      "statement": "Defensie heeft al de perfecte oplossing voor drone-aanvallen.",
      "isTrue": false
    },
    {
      "statement": "De tekst suggereert dat Defensie actie onderneemt na drone-incidenten.",
      "isTrue": true
    },
    {
      "statement": "Defensie gaat minder drones gebruiken door deze ontwikkelingen.",
      "isTrue": false
    }
  ]
}