{
  "id": 8,
  "section": "Buitenland",
  "topic": "Buitenland",
  "level": "B1",
  "title": "Speurtocht naar ‘eerste’ drones in Noorwegen en Denemarken levert vooral vragen op",
  "topicNumber": 1,
  "article": {
    "title": "Speurtocht naar ‘eerste’ drones in Noorwegen en Denemarken levert vooral vragen op",
    "summary": "De Denen en Noren sloten als eersten in Europa hun luchthavens wegens drones. Maar bijna twee maanden later is nog niet bevestigd dat er daar effectief vlogen. De Noorse politie staakte haar onderzoek zelfs wegens gebrek aan bewijs. In België worden minstens zeventien incidenten onderzocht."
  },
  "vocabulary": {
    "words": [
      {
        "word": "bewijs",
        "definition": "materiaal of informatie die iets bevestigt",
        "sentence": "Zonder ___ kan de politie niets doen.",
        "answer": "bewijs"
      },
      {
        "word": "incidenten",
        "definition": "gebeurtenissen of voorvallen, meestal ongelukkig",
        "sentence": "Er waren verschillende ___ tijdens het festival.",
        "answer": "incidenten"
      },
      {
        "word": "luchthavens",
        "definition": "plaatsen waar vliegtuigen landen en opstijgen",
        "sentence": "We wachten in de ___ tot ons vliegtuig vertrekt.",
        "answer": "luchthavens"
      },
      {
        "word": "effectief",
        "definition": "echt, daadwerkelijk",
        "sentence": "De maatregel was ___ nuttig.",
        "answer": "effectief"
      },
      {
        "word": "onderzoek",
        "definition": "het bestuderen of uitzoeken van iets",
        "sentence": "Het politie- ___ naar de diefstal duurt lang.",
        "answer": "onderzoek"
      }
    ],
    "fillInBlanks": [
      {
        "sentence": "Zonder ___ kan de politie niets doen.",
        "answer": "bewijs"
      },
      {
        "sentence": "We wachten in de ___ tot ons vliegtuig vertrekt.",
        "answer": "luchthavens"
      },
      {
        "sentence": "Het politie- ___ naar de diefstal duurt lang.",
        "answer": "onderzoek"
      }
    ]
  },
  "multipleChoice": [
    {
      "question": "Waarom sloten Denemarken en Noorwegen hun luchthavens?",
      "options": [
        "Vanwege sneeuw",
        "Vanwege drones",
        "Vanwege vakantie",
        "Vanwege een feest"
      ],
      "correctAnswer": 2
    },
    {
      "question": "Wat deed de Noorse politie met het onderzoek?",
      "options": [
        "Stopte het",
        "Startte het",
        "Vergat het",
        "Vierde het"
      ],
      "correctAnswer": 1
    },
    {
      "question": "Waar worden incidenten onderzocht?",
      "options": [
        "In Nederland",
        "In Luxemburg",
        "In België",
        "In Duitsland"
      ],
      "correctAnswer": 3
    }
  ],
  "trueFalse": [
    {
      "statement": "Noorwegen en Denemarken hadden als eerste last van drones.",
      "isTrue": true
    },
    {
      "statement": "De Noorse politie stopte het onderzoek omdat het klaar was.",
      "isTrue": false
    },
    {
      "statement": "In België worden minstens zeventien incidenten onderzocht.",
      "isTrue": true
    }
  ]
}