{
  "id": 6,
  "section": "Buitenland",
  "topic": "Buitenland",
  "level": "A1",
  "title": "Catherine Connolly wordt president van Ierland, rivaal erkent nederlaag",
  "topicNumber": 1,
  "article": {
    "title": "Catherine Connolly wordt president van Ierland, rivaal erkent nederlaag",
    "summary": "Catherine Connolly wordt de nieuwe president van Ierland. Haar tegenstander heeft de verkiezing verloren. Catherine Connolly is de nieuwe president."
  },
  "vocabulary": {
    "words": [
      {
        "word": "wordt",
        "definition": "veranderen naar een nieuwe staat",
        "sentence": "Zij ___ de nieuwe leider.",
        "answer": "wordt"
      },
      {
        "word": "rivaal",
        "definition": "iemand met wie je strijdt",
        "sentence": "Hij was mijn ___ in de wedstrijd.",
        "answer": "rivaal"
      },
      {
        "word": "heeft",
        "definition": "hebben, in bezit hebben",
        "sentence": "Zij ___ een mooi huis.",
        "answer": "heeft"
      },
      {
        "word": "nederlaag",
        "definition": "verliezen van een strijd",
        "sentence": "Na de ___ gaf hij op.",
        "answer": "nederlaag"
      },
      {
        "word": "van",
        "definition": "een voorzetsel dat bezit of herkomst aangeeft",
        "sentence": "De hoofdstad ___ Nederland is Amsterdam.",
        "answer": "van"
      }
    ],
    "fillInBlanks": [
      {
        "sentence": "De hoofdstad ___ Nederland is Amsterdam.",
        "answer": "van"
      },
      {
        "sentence": "Zij ___ de nieuwe leider.",
        "answer": "wordt"
      },
      {
        "sentence": "Na de ___ gaf hij op.",
        "answer": "nederlaag"
      }
    ]
  },
  "multipleChoice": [
    {
      "question": "Wie is Catherine Connolly?",
      "options": [
        "Een actrice",
        "De nieuwe president van Ierland",
        "Een Nederlandse politicus",
        "Een leraar"
      ],
      "correctAnswer": 2
    },
    {
      "question": "Wat betekent 'erkent'?",
      "options": [
        "Verliest",
        "Geeft toe",
        "Wint",
        "Is blij"
      ],
      "correctAnswer": 2
    },
    {
      "question": "Wat is een 'rivaal'?",
      "options": [
        "Een vriend",
        "Iemand met wie je strijdt",
        "Een buurman",
        "Een soort voedsel"
      ],
      "correctAnswer": 2
    }
  ],
  "trueFalse": [
    {
      "statement": "Catherine Connolly is de nieuwe president van Ierland.",
      "isTrue": true
    },
    {
      "statement": "Heather Humphreys heeft de verkiezing gewonnen.",
      "isTrue": false
    },
    {
      "statement": "Catherine Connolly wordt de nieuwe president.",
      "isTrue": true
    }
  ]
}