{
  "id": 16,
  "section": "Binnenland",
  "topic": "Binnenland",
  "level": "C1",
  "title": "Strijd tegen Russische corruptie leidt naar Antwerps appartement",
  "topicNumber": 1,
  "article": {
    "title": "Strijd tegen Russische corruptie leidt naar Antwerps appartement",
    "summary": "De strijd tegen Russische corruptie leidt zelfs tot in het Vlinderpaleis. Op het spel staat een eerbetoon aan Sergej Magnitski en een Antwerps appartement waarvan wordt aangenomen dat het aangekocht is met geld van de beruchte fraudezaak."
  },
  "vocabulary": {
    "words": [
      {
        "word": "strijd",
        "definition": "een hevige, langdurige strijd of conflict",
        "sentence": "De politieke ___ in het land leidde tot grote spanningen.",
        "answer": "strijd"
      },
      {
        "word": "corruptie",
        "definition": "het misbruik van macht voor persoonlijk gewin",
        "sentence": "Wijdverspreide ___ ondermijnt het vertrouwen in de overheid.",
        "answer": "corruptie"
      },
      {
        "word": "aangenomen",
        "definition": "verondersteld, aangenomen (van een feit of situatie)",
        "sentence": "Het werd ___ dat de zaak al gesloten was.",
        "answer": "aangenomen"
      },
      {
        "word": "aangekocht",
        "definition": "verleden deelwoord van aankopen; gekocht",
        "sentence": "Hij heeft het huis ___ via een online veiling.",
        "answer": "aangekocht"
      },
      {
        "word": "berucht",
        "definition": "berucht; bekend om slechte redenen",
        "sentence": "De straat is ___ vanwege de vele inbraken.",
        "answer": "berucht"
      }
    ],
    "fillInBlanks": [
      {
        "sentence": "De straat is ___ vanwege de vele inbraken.",
        "answer": "berucht"
      },
      {
        "sentence": "Hij heeft het huis ___ via een online veiling.",
        "answer": "aangekocht"
      },
      {
        "sentence": "De politieke ___ in het land leidde tot grote spanningen.",
        "answer": "strijd"
      }
    ]
  },
  "multipleChoice": [
    {
      "question": "Waar refereert 'Vlinderpaleis' primair naar in deze context?",
      "options": [
        "Een operagebouw",
        "Een metafoor voor fragiliteit",
        "Een bekend café in Antwerpen",
        "Een type kunstwerk"
      ],
      "correctAnswer": 3
    },
    {
      "question": "Wat is de hoofdgedachte van de samenvatting?",
      "options": [
        "De strijd tegen corruptie is geconcentreerd in één specifiek gebouw.",
        "Antwerpen is het centrum van de wereldwijde anti-corruptie inspanningen.",
        "Een eerbetoon en een aankoop zijn symbolisch voor de bredere corruptiebestrijding.",
        "Sergei Magnitski is de eigenaar van het appartement in Antwerpen."
      ],
      "correctAnswer": 2
    },
    {
      "question": "Wat impliceert de tekst over de aankoop van het appartement?",
      "options": [
        "Het werd officieel bevestigd door de Russische overheid.",
        "Het was een direct resultaat van de fraudezaak.",
        "Het was in handen van een onbekende magnaat.",
        "Het werd alleen aangenomen, niet bewezen."
      ],
      "correctAnswer": 1
    }
  ],
  "trueFalse": [
    {
      "statement": "Het Vlinderpaleis is de locatie waar de corruptie plaatsvond.",
      "isTrue": false
    },
    {
      "statement": "De fraudezaak is direct gerelateerd aan de aankoop van het Antwerpse appartement.",
      "isTrue": true
    },
    {
      "statement": "Sergei Magnitski is de eigenaar van het appartement in Antwerpen.",
      "isTrue": false
    }
  ]
}