{
  "id": 9,
  "section": "Buitenland",
  "topic": "Buitenland",
  "level": "B2",
  "title": "Al-Qaeda-rebellen houden Malinese hoofdstad in economische wurggreep",
  "topicNumber": 1,
  "article": {
    "title": "Al-Qaeda-rebellen houden Malinese hoofdstad in economische wurggreep",
    "summary": "In Mali staat het militaire regime onder zware druk. Al-Qaeda-strijders hebben een economische blokkade ingevoerd tegen Bamako, waardoor de stad zonder brandstof dreigt te vallen. De rebellen hopen dat er een opstand uitbreekt, zodat zij de macht kunnen grijpen."
  },
  "vocabulary": {
    "words": [
      {
        "word": "regime",
        "definition": "een regering of bestuursorgaan, vooral een autoritair regime",
        "sentence": "Het militaire ___ heeft de macht in Mali.",
        "answer": "regime"
      },
      {
        "word": "blokkade",
        "definition": "een blokkering, iets dat de doorgang belemmert",
        "sentence": "De rebellen hebben een ___ opgeworpen.",
        "answer": "blokkade"
      },
      {
        "word": "brandstof",
        "definition": "brandstof, iets dat energie levert, zoals benzine of gas",
        "sentence": "Zonder ___ kan de economie niet draaien.",
        "answer": "brandstof"
      },
      {
        "word": "dreigt",
        "definition": "iets wat waarschijnlijk gaat gebeuren, vaak iets negatiefs",
        "sentence": "De stad ___ zonder brandstof te vallen.",
        "answer": "dreigt"
      },
      {
        "word": "macht",
        "definition": "controle of autoriteit, de mogelijkheid om te controleren",
        "sentence": "De rebellen willen de ___ overnemen.",
        "answer": "macht"
      }
    ],
    "fillInBlanks": [
      {
        "sentence": "Zonder ___ kan de economie niet draaien.",
        "answer": "brandstof"
      },
      {
        "sentence": "De rebellen willen de ___ overnemen.",
        "answer": "macht"
      },
      {
        "sentence": "Het militaire ___ heeft de macht in Mali.",
        "answer": "regime"
      }
    ]
  },
  "multipleChoice": [
    {
      "question": "Wat is het hoofddoel van de rebellen in deze situatie?",
      "options": [
        "De hoofdstad verwoesten",
        "De bevolking tegen zich in opstand laten komen",
        "De economie volledig overnemen",
        "De regering ten val brengen via een opstand"
      ],
      "correctAnswer": 4
    },
    {
      "question": "Wat is de rol van de economische blokkade in de strategie van de rebellen?",
      "options": [
        "Het is een afleidingsmanoeuvre voor een militaire aanval.",
        "Het verzwakt de stad en maakt de bevolking ontevreden, zodat ze de rebellen steunen.",
        "Het is een manier om de regering te dwingen tot overgave zonder een schot te lossen.",
        "Het is een test om te zien of de regering reageert."
      ],
      "correctAnswer": 2
    },
    {
      "question": "Wat is de huidige toestand van de hoofdstad Bamako volgens de tekst?",
      "options": [
        "Het is al volledig in handen van de rebellen.",
        "Het valt nog steeds onder het gezag van het militaire regime.",
        "Het is onbekend, de tekst noemt het niet.",
        "Het is een neutrale zone waar niemand de controle heeft."
      ],
      "correctAnswer": 2
    }
  ],
  "trueFalse": [
    {
      "statement": "De rebellen hebben Bamako al ingenomen met hun troepen.",
      "isTrue": false
    },
    {
      "statement": "De economische blokkade zorgt voor tekorten in de stad.",
      "isTrue": true
    },
    {
      "statement": "Het militaire regime wordt gesteund door de meeste inwoners.",
      "isTrue": false
    }
  ]
}